ton_connect/__init__.py
ton_connect/bridge.py
ton_connect/connector.py
ton_connect/crypto.py
ton_connect/misc.py
ton_connect/model/__init__.py
ton_connect/model/app/__init__.py
ton_connect/model/app/error.py
ton_connect/model/app/request.py
ton_connect/model/app/response.py
ton_connect/model/app/wallet.py
ton_connect/model/error.py
ton_connect/model/misc.py
ton_connect/model/model.py
ton_connect/model/response.py
ton_connect/model/wallet/__init__.py
ton_connect/model/wallet/device.py
ton_connect/model/wallet/error.py
ton_connect/model/wallet/event.py
ton_connect/model/wallet/response.py
ton_connect/model/wallet/wallet.py
ton_connect/storage.py
ton_connect/types.py
ton_connect_async-0.2.19.dist-info/METADATA
ton_connect_async-0.2.19.dist-info/WHEEL
ton_connect_async-0.2.19.dist-info/RECORD
