Metadata-Version: 2.1
Name: ton-connect-async
Version: 0.2.19
Summary: Python SDK for TON Connect
Home-page: https://github.com/yurzs/ton-connect
License: MIT
Author: Yury Sokov
Author-email: me@yurzs.dev
Requires-Python: >=3.11
Classifier: License :: OSI Approved :: MIT License
Classifier: Programming Language :: Python :: 3
Classifier: Programming Language :: Python :: 3.11
Classifier: Programming Language :: Python :: 3.12
Classifier: Programming Language :: Python :: 3.13
Requires-Dist: certifi (>=2024.6.2)
Requires-Dist: httpx (>=0.28.1,<0.29.0)
Requires-Dist: httpx-sse (>=0.4.0,<0.5.0)
Requires-Dist: pydantic (>=2,<3.0.0)
Requires-Dist: pymongo (>=4.10.1,<5.0.0)
Requires-Dist: pynacl (>=1.5.0,<2.0.0)
Project-URL: Documentation, https://github.com/yurzs/ton-connect
